{"nodes":[0,1,2,3,4,5,6,7,8,9,10,11,12,13,14,15,16,17],"edges":[{"source":0,"target":1,"name":"regions"},{"source":1,"target":2,"name":"vertices"},{"source":1,"target":3,"name":"vertices"},{"source":1,"target":4,"name":"vertices"},{"source":1,"target":5,"name":"vertices"},{"source":1,"target":6,"name":"vertices"},{"source":1,"target":7,"name":"vertices"},{"source":3,"target":8,"name":"incomingTransitions"},{"source":3,"target":9,"name":"regions"},{"source":5,"target":17,"name":"incomingTransitions"},{"source":5,"target":17,"name":"outgoingTransitions"},{"source":6,"target":8,"name":"outgoingTransitions"},{"source":7,"target":16,"name":"incomingTransitions"},{"source":8,"target":3,"name":"target"},{"source":8,"target":6,"name":"source"},{"source":9,"target":10,"name":"vertices"},{"source":9,"target":11,"name":"vertices"},{"source":9,"target":12,"name":"vertices"},{"source":9,"target":13,"name":"vertices"},{"source":9,"target":14,"name":"vertices"},{"source":9,"target":15,"name":"vertices"},{"source":14,"target":16,"name":"outgoingTransitions"},{"source":16,"target":7,"name":"target"},{"source":16,"target":14,"name":"source"},{"source":17,"target":5,"name":"target"},{"source":17,"target":5,"name":"source"}],"nodeTypes":{"0":"Statechart","1":"Region","2":"State","3":"State","4":"Synchronization","5":"Choice","6":"Entry","7":"State","8":"Transition","9":"Region","10":"State","11":"Exit","12":"State","13":"State","14":"Entry","15":"State","16":"Transition","17":"Transition"},"name":"71.xmi"}
