{"nodes":[0,1,2,3,4,5,6,7,8,9,10,11,12,13,14,15,16,17,18],"edges":[{"source":0,"target":1,"name":"elements"},{"source":0,"target":2,"name":"elements"},{"source":0,"target":3,"name":"elements"},{"source":0,"target":4,"name":"elements"},{"source":0,"target":5,"name":"elements"},{"source":0,"target":6,"name":"elements"},{"source":0,"target":7,"name":"elements"},{"source":0,"target":8,"name":"elements"},{"source":0,"target":9,"name":"elements"},{"source":1,"target":10,"name":"foreignKeyColumns"},{"source":1,"target":10,"name":"primaryKeyColumns"},{"source":2,"target":10,"name":"foreignKeyColumns"},{"source":2,"target":11,"name":"primaryKeyColumns"},{"source":3,"target":10,"name":"foreignKeyColumns"},{"source":3,"target":11,"name":"primaryKeyColumns"},{"source":4,"target":10,"name":"foreignKeyColumns"},{"source":4,"target":10,"name":"primaryKeyColumns"},{"source":5,"target":10,"name":"foreignKeyColumns"},{"source":5,"target":10,"name":"primaryKeyColumns"},{"source":6,"target":10,"name":"foreignKeyColumns"},{"source":6,"target":10,"name":"primaryKeyColumns"},{"source":7,"target":12,"name":"columns"},{"source":7,"target":13,"name":"columns"},{"source":7,"target":14,"name":"columns"},{"source":7,"target":15,"name":"columns"},{"source":7,"target":16,"name":"columns"},{"source":7,"target":17,"name":"columns"},{"source":7,"target":18,"name":"columns"},{"source":7,"target":11,"name":"columns"},{"source":7,"target":10,"name":"columns"},{"source":10,"target":3,"name":"foreignReferences"},{"source":10,"target":5,"name":"foreignReferences"},{"source":10,"target":2,"name":"foreignReferences"},{"source":10,"target":6,"name":"foreignReferences"},{"source":10,"target":1,"name":"foreignReferences"},{"source":10,"target":4,"name":"foreignReferences"},{"source":10,"target":5,"name":"primaryReferences"},{"source":10,"target":4,"name":"primaryReferences"},{"source":10,"target":1,"name":"primaryReferences"},{"source":10,"target":6,"name":"primaryReferences"},{"source":11,"target":3,"name":"primaryReferences"},{"source":11,"target":2,"name":"primaryReferences"}],"nodeTypes":{"0":"Database","1":"Reference","2":"Reference","3":"Reference","4":"Reference","5":"Reference","6":"Reference","7":"Table","8":"Table","9":"Table","10":"Column","11":"Column","12":"Column","13":"Column","14":"Column","15":"Column","16":"Column","17":"Column","18":"Column"},"name":"RDS_287_rdsSimplified_result0_11.xmi"}
