{"nodes":[0,1,2,3,4,5,6,7,8,9,10,11,12,13,14,15,16,17,18,19,20,21,22,23,24,25,26,27,28,29,30,31,32,33,34,35,36,37,38,39,40,41,42,43,44,45,46,47,48,49,50,51,52,53,54,55,56,57,58,59,60,61,62,63,64,65,66,67,68,69,70,71,72,73,74,75,76,77,78,79,80,81,82,83,84,85,86,87,88,89,90,91,92,93,94,95,96,97,98,99,100,101,102,103,104,105,106,107,108,109,110,111,112,113,114,115,116,117,118,119,120,121,122,123,124,125,126,127,128,129,130,131,132,133,134,135,136,137,138,139,140,141,142,143,144,145,146,147,148,149,150,151,152,153,154,155,156,157,158,159,160,161,162,163,164,165,166,167,168,169,170,171,172,173,174,175,176,177,178,179,180,181,182,183,184,185,186,187,188,189,190,191,192,193,194,195,196,197,198,199,200,201,202,203,204,205,206,207,208,209,210,211,212,213,214,215,216,217,218,219,220,221,222,223,224,225,226,227,228,229,230,231,232,233,234,235,236,237,238,239,240,241,242,243,244,245,246,247,248,249,250,251,252,253,254,255,256,257,258,259,260,261,262,263,264,265,266,267,268,269,270,271,272,273,274,275,276,277,278,279,280,281,282,283,284,285,286,287,288,289,290,291,292,293,294,295,296,297,298,299,300,301,302,303,304,305,306,307,308,309,310,311,312,313,314,315,316,317,318,319,320,321,322,323,324,325,326,327,328,329,330,331,332,333,334,335,336,337,338,339,340,341,342,343,344,345,346,347,348,349,350,351,352,353,354,355,356,357,358,359,360,361,362,363,364,365,366,367,368,369,370,371,372,373,374,375,376,377,378,379,380,381,382,383,384,385,386,387,388,389],"edges":[{"source":0,"target":1,"name":"eClassifiers"},{"source":0,"target":2,"name":"eClassifiers"},{"source":0,"target":3,"name":"eClassifiers"},{"source":0,"target":4,"name":"eClassifiers"},{"source":0,"target":5,"name":"eClassifiers"},{"source":0,"target":6,"name":"eClassifiers"},{"source":0,"target":7,"name":"eClassifiers"},{"source":0,"target":8,"name":"eClassifiers"},{"source":0,"target":9,"name":"eClassifiers"},{"source":0,"target":10,"name":"eClassifiers"},{"source":0,"target":11,"name":"eClassifiers"},{"source":0,"target":12,"name":"eClassifiers"},{"source":0,"target":13,"name":"eClassifiers"},{"source":0,"target":14,"name":"eClassifiers"},{"source":0,"target":15,"name":"eClassifiers"},{"source":0,"target":16,"name":"eClassifiers"},{"source":0,"target":17,"name":"eClassifiers"},{"source":0,"target":18,"name":"eClassifiers"},{"source":0,"target":19,"name":"eClassifiers"},{"source":0,"target":20,"name":"eClassifiers"},{"source":0,"target":21,"name":"eClassifiers"},{"source":0,"target":22,"name":"eClassifiers"},{"source":0,"target":23,"name":"eClassifiers"},{"source":0,"target":24,"name":"eClassifiers"},{"source":0,"target":25,"name":"eClassifiers"},{"source":0,"target":26,"name":"eClassifiers"},{"source":0,"target":27,"name":"eClassifiers"},{"source":0,"target":28,"name":"eClassifiers"},{"source":0,"target":29,"name":"eClassifiers"},{"source":0,"target":30,"name":"eClassifiers"},{"source":0,"target":31,"name":"eClassifiers"},{"source":0,"target":32,"name":"eClassifiers"},{"source":0,"target":33,"name":"eClassifiers"},{"source":0,"target":34,"name":"eClassifiers"},{"source":0,"target":35,"name":"eClassifiers"},{"source":0,"target":36,"name":"eClassifiers"},{"source":0,"target":37,"name":"eClassifiers"},{"source":0,"target":38,"name":"eClassifiers"},{"source":0,"target":39,"name":"eClassifiers"},{"source":0,"target":40,"name":"eClassifiers"},{"source":0,"target":41,"name":"eClassifiers"},{"source":0,"target":42,"name":"eClassifiers"},{"source":0,"target":43,"name":"eClassifiers"},{"source":0,"target":44,"name":"eClassifiers"},{"source":0,"target":45,"name":"eClassifiers"},{"source":0,"target":46,"name":"eClassifiers"},{"source":0,"target":47,"name":"eClassifiers"},{"source":0,"target":48,"name":"eClassifiers"},{"source":0,"target":49,"name":"eClassifiers"},{"source":0,"target":50,"name":"eClassifiers"},{"source":0,"target":51,"name":"eClassifiers"},{"source":0,"target":52,"name":"eClassifiers"},{"source":0,"target":53,"name":"eClassifiers"},{"source":0,"target":54,"name":"eClassifiers"},{"source":0,"target":55,"name":"eClassifiers"},{"source":0,"target":56,"name":"eClassifiers"},{"source":0,"target":57,"name":"eClassifiers"},{"source":0,"target":58,"name":"eClassifiers"},{"source":0,"target":59,"name":"eClassifiers"},{"source":0,"target":60,"name":"eClassifiers"},{"source":0,"target":61,"name":"eClassifiers"},{"source":0,"target":62,"name":"eClassifiers"},{"source":0,"target":63,"name":"eClassifiers"},{"source":0,"target":64,"name":"eClassifiers"},{"source":0,"target":65,"name":"eClassifiers"},{"source":0,"target":66,"name":"eClassifiers"},{"source":0,"target":67,"name":"eClassifiers"},{"source":0,"target":68,"name":"eClassifiers"},{"source":0,"target":69,"name":"eClassifiers"},{"source":0,"target":70,"name":"eClassifiers"},{"source":0,"target":71,"name":"eClassifiers"},{"source":0,"target":72,"name":"eClassifiers"},{"source":0,"target":73,"name":"eClassifiers"},{"source":0,"target":74,"name":"eClassifiers"},{"source":0,"target":75,"name":"eClassifiers"},{"source":0,"target":76,"name":"eClassifiers"},{"source":0,"target":77,"name":"eClassifiers"},{"source":0,"target":78,"name":"eClassifiers"},{"source":0,"target":79,"name":"eClassifiers"},{"source":0,"target":80,"name":"eClassifiers"},{"source":0,"target":81,"name":"eClassifiers"},{"source":0,"target":82,"name":"eClassifiers"},{"source":0,"target":83,"name":"eClassifiers"},{"source":0,"target":84,"name":"eClassifiers"},{"source":0,"target":85,"name":"eClassifiers"},{"source":0,"target":86,"name":"eClassifiers"},{"source":0,"target":87,"name":"eClassifiers"},{"source":0,"target":88,"name":"eClassifiers"},{"source":0,"target":89,"name":"eClassifiers"},{"source":0,"target":90,"name":"eClassifiers"},{"source":0,"target":91,"name":"eClassifiers"},{"source":0,"target":92,"name":"eClassifiers"},{"source":0,"target":93,"name":"eClassifiers"},{"source":0,"target":94,"name":"eClassifiers"},{"source":0,"target":95,"name":"eClassifiers"},{"source":0,"target":96,"name":"eClassifiers"},{"source":0,"target":97,"name":"eClassifiers"},{"source":0,"target":98,"name":"eClassifiers"},{"source":0,"target":99,"name":"eClassifiers"},{"source":0,"target":100,"name":"eClassifiers"},{"source":0,"target":101,"name":"eClassifiers"},{"source":0,"target":102,"name":"eClassifiers"},{"source":0,"target":103,"name":"eClassifiers"},{"source":0,"target":104,"name":"eClassifiers"},{"source":0,"target":105,"name":"eClassifiers"},{"source":0,"target":106,"name":"eClassifiers"},{"source":0,"target":107,"name":"eClassifiers"},{"source":0,"target":108,"name":"eClassifiers"},{"source":0,"target":109,"name":"eClassifiers"},{"source":0,"target":110,"name":"eClassifiers"},{"source":0,"target":111,"name":"eClassifiers"},{"source":0,"target":112,"name":"eClassifiers"},{"source":0,"target":113,"name":"eClassifiers"},{"source":0,"target":114,"name":"eClassifiers"},{"source":0,"target":115,"name":"eClassifiers"},{"source":0,"target":116,"name":"eClassifiers"},{"source":0,"target":117,"name":"eClassifiers"},{"source":0,"target":118,"name":"eClassifiers"},{"source":0,"target":119,"name":"eClassifiers"},{"source":0,"target":120,"name":"eClassifiers"},{"source":0,"target":121,"name":"eClassifiers"},{"source":0,"target":122,"name":"eClassifiers"},{"source":0,"target":123,"name":"eClassifiers"},{"source":0,"target":124,"name":"eClassifiers"},{"source":0,"target":125,"name":"eClassifiers"},{"source":0,"target":126,"name":"eClassifiers"},{"source":0,"target":127,"name":"eClassifiers"},{"source":0,"target":128,"name":"eClassifiers"},{"source":0,"target":129,"name":"eClassifiers"},{"source":0,"target":130,"name":"eClassifiers"},{"source":0,"target":131,"name":"eClassifiers"},{"source":0,"target":132,"name":"eClassifiers"},{"source":0,"target":133,"name":"eClassifiers"},{"source":0,"target":134,"name":"eClassifiers"},{"source":0,"target":135,"name":"eClassifiers"},{"source":0,"target":136,"name":"eClassifiers"},{"source":0,"target":137,"name":"eClassifiers"},{"source":0,"target":138,"name":"eClassifiers"},{"source":0,"target":139,"name":"eClassifiers"},{"source":0,"target":140,"name":"eClassifiers"},{"source":0,"target":141,"name":"eClassifiers"},{"source":0,"target":142,"name":"eClassifiers"},{"source":0,"target":143,"name":"eClassifiers"},{"source":0,"target":144,"name":"eClassifiers"},{"source":0,"target":145,"name":"eClassifiers"},{"source":0,"target":146,"name":"eClassifiers"},{"source":0,"target":147,"name":"eClassifiers"},{"source":1,"target":0,"name":"ePackage"},{"source":2,"target":0,"name":"ePackage"},{"source":2,"target":148,"name":"eLiterals"},{"source":2,"target":149,"name":"eLiterals"},{"source":2,"target":150,"name":"eLiterals"},{"source":2,"target":151,"name":"eLiterals"},{"source":2,"target":152,"name":"eLiterals"},{"source":2,"target":153,"name":"eLiterals"},{"source":2,"target":154,"name":"eLiterals"},{"source":3,"target":0,"name":"ePackage"},{"source":4,"target":0,"name":"ePackage"},{"source":4,"target":155,"name":"eLiterals"},{"source":4,"target":156,"name":"eLiterals"},{"source":4,"target":157,"name":"eLiterals"},{"source":4,"target":158,"name":"eLiterals"},{"source":4,"target":159,"name":"eLiterals"},{"source":5,"target":0,"name":"ePackage"},{"source":6,"target":0,"name":"ePackage"},{"source":7,"target":0,"name":"ePackage"},{"source":8,"target":0,"name":"ePackage"},{"source":9,"target":0,"name":"ePackage"},{"source":10,"target":0,"name":"ePackage"},{"source":10,"target":160,"name":"eLiterals"},{"source":10,"target":161,"name":"eLiterals"},{"source":10,"target":162,"name":"eLiterals"},{"source":11,"target":0,"name":"ePackage"},{"source":12,"target":0,"name":"ePackage"},{"source":13,"target":0,"name":"ePackage"},{"source":14,"target":0,"name":"ePackage"},{"source":15,"target":0,"name":"ePackage"},{"source":15,"target":163,"name":"eLiterals"},{"source":15,"target":164,"name":"eLiterals"},{"source":15,"target":165,"name":"eLiterals"},{"source":15,"target":166,"name":"eLiterals"},{"source":15,"target":167,"name":"eLiterals"},{"source":15,"target":168,"name":"eLiterals"},{"source":15,"target":169,"name":"eLiterals"},{"source":15,"target":170,"name":"eLiterals"},{"source":15,"target":171,"name":"eLiterals"},{"source":15,"target":172,"name":"eLiterals"},{"source":15,"target":173,"name":"eLiterals"},{"source":15,"target":174,"name":"eLiterals"},{"source":16,"target":0,"name":"ePackage"},{"source":17,"target":0,"name":"ePackage"},{"source":18,"target":0,"name":"ePackage"},{"source":18,"target":175,"name":"eLiterals"},{"source":18,"target":176,"name":"eLiterals"},{"source":18,"target":177,"name":"eLiterals"},{"source":18,"target":178,"name":"eLiterals"},{"source":18,"target":179,"name":"eLiterals"},{"source":19,"target":0,"name":"ePackage"},{"source":20,"target":0,"name":"ePackage"},{"source":21,"target":0,"name":"ePackage"},{"source":22,"target":0,"name":"ePackage"},{"source":23,"target":0,"name":"ePackage"},{"source":23,"target":180,"name":"eLiterals"},{"source":23,"target":181,"name":"eLiterals"},{"source":24,"target":0,"name":"ePackage"},{"source":25,"target":0,"name":"ePackage"},{"source":26,"target":0,"name":"ePackage"},{"source":26,"target":182,"name":"eLiterals"},{"source":26,"target":183,"name":"eLiterals"},{"source":26,"target":184,"name":"eLiterals"},{"source":26,"target":185,"name":"eLiterals"},{"source":26,"target":186,"name":"eLiterals"},{"source":27,"target":0,"name":"ePackage"},{"source":28,"target":0,"name":"ePackage"},{"source":29,"target":0,"name":"ePackage"},{"source":29,"target":187,"name":"eLiterals"},{"source":29,"target":188,"name":"eLiterals"},{"source":29,"target":189,"name":"eLiterals"},{"source":30,"target":0,"name":"ePackage"},{"source":31,"target":0,"name":"ePackage"},{"source":32,"target":0,"name":"ePackage"},{"source":32,"target":190,"name":"eLiterals"},{"source":32,"target":191,"name":"eLiterals"},{"source":32,"target":192,"name":"eLiterals"},{"source":32,"target":193,"name":"eLiterals"},{"source":32,"target":194,"name":"eLiterals"},{"source":33,"target":0,"name":"ePackage"},{"source":34,"target":0,"name":"ePackage"},{"source":35,"target":0,"name":"ePackage"},{"source":36,"target":0,"name":"ePackage"},{"source":37,"target":0,"name":"ePackage"},{"source":38,"target":0,"name":"ePackage"},{"source":39,"target":0,"name":"ePackage"},{"source":39,"target":195,"name":"eLiterals"},{"source":39,"target":196,"name":"eLiterals"},{"source":39,"target":197,"name":"eLiterals"},{"source":39,"target":198,"name":"eLiterals"},{"source":39,"target":199,"name":"eLiterals"},{"source":39,"target":200,"name":"eLiterals"},{"source":39,"target":201,"name":"eLiterals"},{"source":39,"target":202,"name":"eLiterals"},{"source":39,"target":203,"name":"eLiterals"},{"source":39,"target":204,"name":"eLiterals"},{"source":39,"target":205,"name":"eLiterals"},{"source":39,"target":206,"name":"eLiterals"},{"source":39,"target":207,"name":"eLiterals"},{"source":39,"target":208,"name":"eLiterals"},{"source":39,"target":209,"name":"eLiterals"},{"source":39,"target":210,"name":"eLiterals"},{"source":39,"target":211,"name":"eLiterals"},{"source":40,"target":0,"name":"ePackage"},{"source":41,"target":0,"name":"ePackage"},{"source":42,"target":0,"name":"ePackage"},{"source":43,"target":0,"name":"ePackage"},{"source":43,"target":212,"name":"eLiterals"},{"source":43,"target":213,"name":"eLiterals"},{"source":43,"target":214,"name":"eLiterals"},{"source":43,"target":215,"name":"eLiterals"},{"source":43,"target":216,"name":"eLiterals"},{"source":43,"target":217,"name":"eLiterals"},{"source":43,"target":218,"name":"eLiterals"},{"source":44,"target":0,"name":"ePackage"},{"source":45,"target":0,"name":"ePackage"},{"source":46,"target":0,"name":"ePackage"},{"source":46,"target":219,"name":"eLiterals"},{"source":46,"target":220,"name":"eLiterals"},{"source":47,"target":0,"name":"ePackage"},{"source":48,"target":0,"name":"ePackage"},{"source":49,"target":0,"name":"ePackage"},{"source":50,"target":0,"name":"ePackage"},{"source":51,"target":0,"name":"ePackage"},{"source":51,"target":221,"name":"eLiterals"},{"source":51,"target":222,"name":"eLiterals"},{"source":51,"target":223,"name":"eLiterals"},{"source":52,"target":0,"name":"ePackage"},{"source":53,"target":0,"name":"ePackage"},{"source":54,"target":0,"name":"ePackage"},{"source":54,"target":224,"name":"eLiterals"},{"source":54,"target":225,"name":"eLiterals"},{"source":54,"target":226,"name":"eLiterals"},{"source":54,"target":227,"name":"eLiterals"},{"source":54,"target":228,"name":"eLiterals"},{"source":54,"target":229,"name":"eLiterals"},{"source":54,"target":230,"name":"eLiterals"},{"source":54,"target":231,"name":"eLiterals"},{"source":54,"target":232,"name":"eLiterals"},{"source":54,"target":233,"name":"eLiterals"},{"source":54,"target":234,"name":"eLiterals"},{"source":54,"target":235,"name":"eLiterals"},{"source":54,"target":236,"name":"eLiterals"},{"source":55,"target":0,"name":"ePackage"},{"source":56,"target":0,"name":"ePackage"},{"source":57,"target":0,"name":"ePackage"},{"source":57,"target":237,"name":"eLiterals"},{"source":57,"target":238,"name":"eLiterals"},{"source":57,"target":239,"name":"eLiterals"},{"source":57,"target":240,"name":"eLiterals"},{"source":57,"target":241,"name":"eLiterals"},{"source":58,"target":0,"name":"ePackage"},{"source":59,"target":0,"name":"ePackage"},{"source":60,"target":0,"name":"ePackage"},{"source":60,"target":242,"name":"eLiterals"},{"source":60,"target":243,"name":"eLiterals"},{"source":60,"target":244,"name":"eLiterals"},{"source":60,"target":245,"name":"eLiterals"},{"source":60,"target":246,"name":"eLiterals"},{"source":60,"target":247,"name":"eLiterals"},{"source":60,"target":248,"name":"eLiterals"},{"source":60,"target":249,"name":"eLiterals"},{"source":60,"target":250,"name":"eLiterals"},{"source":60,"target":251,"name":"eLiterals"},{"source":60,"target":252,"name":"eLiterals"},{"source":60,"target":253,"name":"eLiterals"},{"source":60,"target":254,"name":"eLiterals"},{"source":60,"target":255,"name":"eLiterals"},{"source":60,"target":256,"name":"eLiterals"},{"source":60,"target":257,"name":"eLiterals"},{"source":61,"target":0,"name":"ePackage"},{"source":62,"target":0,"name":"ePackage"},{"source":63,"target":0,"name":"ePackage"},{"source":63,"target":258,"name":"eLiterals"},{"source":63,"target":259,"name":"eLiterals"},{"source":64,"target":0,"name":"ePackage"},{"source":65,"target":0,"name":"ePackage"},{"source":66,"target":0,"name":"ePackage"},{"source":66,"target":260,"name":"eLiterals"},{"source":66,"target":261,"name":"eLiterals"},{"source":66,"target":262,"name":"eLiterals"},{"source":66,"target":263,"name":"eLiterals"},{"source":67,"target":0,"name":"ePackage"},{"source":68,"target":0,"name":"ePackage"},{"source":69,"target":0,"name":"ePackage"},{"source":70,"target":0,"name":"ePackage"},{"source":71,"target":0,"name":"ePackage"},{"source":71,"target":264,"name":"eLiterals"},{"source":71,"target":265,"name":"eLiterals"},{"source":71,"target":266,"name":"eLiterals"},{"source":72,"target":0,"name":"ePackage"},{"source":73,"target":0,"name":"ePackage"},{"source":74,"target":0,"name":"ePackage"},{"source":75,"target":0,"name":"ePackage"},{"source":76,"target":0,"name":"ePackage"},{"source":77,"target":0,"name":"ePackage"},{"source":77,"target":267,"name":"eLiterals"},{"source":77,"target":268,"name":"eLiterals"},{"source":78,"target":0,"name":"ePackage"},{"source":79,"target":0,"name":"ePackage"},{"source":80,"target":0,"name":"ePackage"},{"source":80,"target":269,"name":"eLiterals"},{"source":80,"target":270,"name":"eLiterals"},{"source":80,"target":271,"name":"eLiterals"},{"source":80,"target":272,"name":"eLiterals"},{"source":80,"target":273,"name":"eLiterals"},{"source":80,"target":274,"name":"eLiterals"},{"source":80,"target":275,"name":"eLiterals"},{"source":81,"target":0,"name":"ePackage"},{"source":82,"target":0,"name":"ePackage"},{"source":83,"target":0,"name":"ePackage"},{"source":83,"target":276,"name":"eLiterals"},{"source":83,"target":277,"name":"eLiterals"},{"source":83,"target":278,"name":"eLiterals"},{"source":84,"target":0,"name":"ePackage"},{"source":85,"target":0,"name":"ePackage"},{"source":86,"target":0,"name":"ePackage"},{"source":86,"target":279,"name":"eLiterals"},{"source":86,"target":280,"name":"eLiterals"},{"source":86,"target":281,"name":"eLiterals"},{"source":86,"target":282,"name":"eLiterals"},{"source":87,"target":0,"name":"ePackage"},{"source":88,"target":0,"name":"ePackage"},{"source":89,"target":0,"name":"ePackage"},{"source":90,"target":0,"name":"ePackage"},{"source":90,"target":283,"name":"eLiterals"},{"source":90,"target":284,"name":"eLiterals"},{"source":91,"target":0,"name":"ePackage"},{"source":92,"target":0,"name":"ePackage"},{"source":93,"target":0,"name":"ePackage"},{"source":94,"target":0,"name":"ePackage"},{"source":95,"target":0,"name":"ePackage"},{"source":95,"target":285,"name":"eLiterals"},{"source":95,"target":286,"name":"eLiterals"},{"source":95,"target":287,"name":"eLiterals"},{"source":95,"target":288,"name":"eLiterals"},{"source":95,"target":289,"name":"eLiterals"},{"source":95,"target":290,"name":"eLiterals"},{"source":95,"target":291,"name":"eLiterals"},{"source":96,"target":0,"name":"ePackage"},{"source":97,"target":0,"name":"ePackage"},{"source":98,"target":0,"name":"ePackage"},{"source":98,"target":292,"name":"eLiterals"},{"source":98,"target":293,"name":"eLiterals"},{"source":98,"target":294,"name":"eLiterals"},{"source":98,"target":295,"name":"eLiterals"},{"source":98,"target":296,"name":"eLiterals"},{"source":98,"target":297,"name":"eLiterals"},{"source":98,"target":298,"name":"eLiterals"},{"source":98,"target":299,"name":"eLiterals"},{"source":98,"target":300,"name":"eLiterals"},{"source":99,"target":0,"name":"ePackage"},{"source":100,"target":0,"name":"ePackage"},{"source":101,"target":0,"name":"ePackage"},{"source":101,"target":301,"name":"eLiterals"},{"source":101,"target":302,"name":"eLiterals"},{"source":101,"target":303,"name":"eLiterals"},{"source":101,"target":304,"name":"eLiterals"},{"source":101,"target":305,"name":"eLiterals"},{"source":101,"target":306,"name":"eLiterals"},{"source":101,"target":307,"name":"eLiterals"},{"source":101,"target":308,"name":"eLiterals"},{"source":101,"target":309,"name":"eLiterals"},{"source":101,"target":310,"name":"eLiterals"},{"source":101,"target":311,"name":"eLiterals"},{"source":101,"target":312,"name":"eLiterals"},{"source":101,"target":313,"name":"eLiterals"},{"source":101,"target":314,"name":"eLiterals"},{"source":101,"target":315,"name":"eLiterals"},{"source":101,"target":316,"name":"eLiterals"},{"source":101,"target":317,"name":"eLiterals"},{"source":101,"target":318,"name":"eLiterals"},{"source":101,"target":319,"name":"eLiterals"},{"source":101,"target":320,"name":"eLiterals"},{"source":101,"target":321,"name":"eLiterals"},{"source":101,"target":322,"name":"eLiterals"},{"source":101,"target":323,"name":"eLiterals"},{"source":101,"target":324,"name":"eLiterals"},{"source":101,"target":325,"name":"eLiterals"},{"source":101,"target":326,"name":"eLiterals"},{"source":101,"target":327,"name":"eLiterals"},{"source":101,"target":328,"name":"eLiterals"},{"source":101,"target":329,"name":"eLiterals"},{"source":101,"target":330,"name":"eLiterals"},{"source":101,"target":331,"name":"eLiterals"},{"source":101,"target":332,"name":"eLiterals"},{"source":101,"target":333,"name":"eLiterals"},{"source":101,"target":334,"name":"eLiterals"},{"source":101,"target":335,"name":"eLiterals"},{"source":101,"target":336,"name":"eLiterals"},{"source":101,"target":337,"name":"eLiterals"},{"source":101,"target":338,"name":"eLiterals"},{"source":101,"target":339,"name":"eLiterals"},{"source":101,"target":340,"name":"eLiterals"},{"source":101,"target":341,"name":"eLiterals"},{"source":101,"target":342,"name":"eLiterals"},{"source":101,"target":343,"name":"eLiterals"},{"source":101,"target":344,"name":"eLiterals"},{"source":102,"target":0,"name":"ePackage"},{"source":103,"target":0,"name":"ePackage"},{"source":104,"target":0,"name":"ePackage"},{"source":104,"target":345,"name":"eLiterals"},{"source":104,"target":346,"name":"eLiterals"},{"source":104,"target":347,"name":"eLiterals"},{"source":104,"target":348,"name":"eLiterals"},{"source":105,"target":0,"name":"ePackage"},{"source":106,"target":0,"name":"ePackage"},{"source":107,"target":0,"name":"ePackage"},{"source":107,"target":349,"name":"eLiterals"},{"source":107,"target":350,"name":"eLiterals"},{"source":107,"target":351,"name":"eLiterals"},{"source":107,"target":352,"name":"eLiterals"},{"source":107,"target":353,"name":"eLiterals"},{"source":108,"target":0,"name":"ePackage"},{"source":109,"target":0,"name":"ePackage"},{"source":110,"target":0,"name":"ePackage"},{"source":110,"target":354,"name":"eLiterals"},{"source":110,"target":355,"name":"eLiterals"},{"source":110,"target":356,"name":"eLiterals"},{"source":111,"target":0,"name":"ePackage"},{"source":112,"target":0,"name":"ePackage"},{"source":113,"target":0,"name":"ePackage"},{"source":114,"target":0,"name":"ePackage"},{"source":115,"target":0,"name":"ePackage"},{"source":115,"target":357,"name":"eLiterals"},{"source":115,"target":358,"name":"eLiterals"},{"source":115,"target":359,"name":"eLiterals"},{"source":115,"target":360,"name":"eLiterals"},{"source":116,"target":0,"name":"ePackage"},{"source":117,"target":0,"name":"ePackage"},{"source":118,"target":0,"name":"ePackage"},{"source":118,"target":361,"name":"eLiterals"},{"source":118,"target":362,"name":"eLiterals"},{"source":118,"target":363,"name":"eLiterals"},{"source":118,"target":364,"name":"eLiterals"},{"source":118,"target":365,"name":"eLiterals"},{"source":119,"target":0,"name":"ePackage"},{"source":120,"target":0,"name":"ePackage"},{"source":121,"target":0,"name":"ePackage"},{"source":122,"target":0,"name":"ePackage"},{"source":123,"target":0,"name":"ePackage"},{"source":123,"target":366,"name":"eLiterals"},{"source":123,"target":367,"name":"eLiterals"},{"source":123,"target":368,"name":"eLiterals"},{"source":124,"target":0,"name":"ePackage"},{"source":125,"target":0,"name":"ePackage"},{"source":126,"target":0,"name":"ePackage"},{"source":126,"target":369,"name":"eLiterals"},{"source":126,"target":370,"name":"eLiterals"},{"source":127,"target":0,"name":"ePackage"},{"source":128,"target":0,"name":"ePackage"},{"source":129,"target":0,"name":"ePackage"},{"source":129,"target":371,"name":"eLiterals"},{"source":129,"target":372,"name":"eLiterals"},{"source":129,"target":373,"name":"eLiterals"},{"source":130,"target":0,"name":"ePackage"},{"source":131,"target":0,"name":"ePackage"},{"source":132,"target":0,"name":"ePackage"},{"source":132,"target":374,"name":"eLiterals"},{"source":132,"target":375,"name":"eLiterals"},{"source":132,"target":376,"name":"eLiterals"},{"source":132,"target":377,"name":"eLiterals"},{"source":132,"target":378,"name":"eLiterals"},{"source":132,"target":379,"name":"eLiterals"},{"source":132,"target":380,"name":"eLiterals"},{"source":132,"target":381,"name":"eLiterals"},{"source":133,"target":0,"name":"ePackage"},{"source":134,"target":0,"name":"ePackage"},{"source":135,"target":0,"name":"ePackage"},{"source":135,"target":382,"name":"eLiterals"},{"source":135,"target":383,"name":"eLiterals"},{"source":135,"target":384,"name":"eLiterals"},{"source":135,"target":385,"name":"eLiterals"},{"source":136,"target":0,"name":"ePackage"},{"source":137,"target":0,"name":"ePackage"},{"source":138,"target":0,"name":"ePackage"},{"source":139,"target":0,"name":"ePackage"},{"source":140,"target":0,"name":"ePackage"},{"source":140,"target":386,"name":"eLiterals"},{"source":140,"target":387,"name":"eLiterals"},{"source":141,"target":0,"name":"ePackage"},{"source":142,"target":0,"name":"ePackage"},{"source":143,"target":0,"name":"ePackage"},{"source":144,"target":0,"name":"ePackage"},{"source":145,"target":0,"name":"ePackage"},{"source":145,"target":388,"name":"eLiterals"},{"source":145,"target":389,"name":"eLiterals"},{"source":146,"target":0,"name":"ePackage"},{"source":147,"target":0,"name":"ePackage"},{"source":148,"target":2,"name":"eEnum"},{"source":149,"target":2,"name":"eEnum"},{"source":150,"target":2,"name":"eEnum"},{"source":151,"target":2,"name":"eEnum"},{"source":152,"target":2,"name":"eEnum"},{"source":153,"target":2,"name":"eEnum"},{"source":154,"target":2,"name":"eEnum"},{"source":155,"target":4,"name":"eEnum"},{"source":156,"target":4,"name":"eEnum"},{"source":157,"target":4,"name":"eEnum"},{"source":158,"target":4,"name":"eEnum"},{"source":159,"target":4,"name":"eEnum"},{"source":160,"target":10,"name":"eEnum"},{"source":161,"target":10,"name":"eEnum"},{"source":162,"target":10,"name":"eEnum"},{"source":163,"target":15,"name":"eEnum"},{"source":164,"target":15,"name":"eEnum"},{"source":165,"target":15,"name":"eEnum"},{"source":166,"target":15,"name":"eEnum"},{"source":167,"target":15,"name":"eEnum"},{"source":168,"target":15,"name":"eEnum"},{"source":169,"target":15,"name":"eEnum"},{"source":170,"target":15,"name":"eEnum"},{"source":171,"target":15,"name":"eEnum"},{"source":172,"target":15,"name":"eEnum"},{"source":173,"target":15,"name":"eEnum"},{"source":174,"target":15,"name":"eEnum"},{"source":175,"target":18,"name":"eEnum"},{"source":176,"target":18,"name":"eEnum"},{"source":177,"target":18,"name":"eEnum"},{"source":178,"target":18,"name":"eEnum"},{"source":179,"target":18,"name":"eEnum"},{"source":180,"target":23,"name":"eEnum"},{"source":181,"target":23,"name":"eEnum"},{"source":182,"target":26,"name":"eEnum"},{"source":183,"target":26,"name":"eEnum"},{"source":184,"target":26,"name":"eEnum"},{"source":185,"target":26,"name":"eEnum"},{"source":186,"target":26,"name":"eEnum"},{"source":187,"target":29,"name":"eEnum"},{"source":188,"target":29,"name":"eEnum"},{"source":189,"target":29,"name":"eEnum"},{"source":190,"target":32,"name":"eEnum"},{"source":191,"target":32,"name":"eEnum"},{"source":192,"target":32,"name":"eEnum"},{"source":193,"target":32,"name":"eEnum"},{"source":194,"target":32,"name":"eEnum"},{"source":195,"target":39,"name":"eEnum"},{"source":196,"target":39,"name":"eEnum"},{"source":197,"target":39,"name":"eEnum"},{"source":198,"target":39,"name":"eEnum"},{"source":199,"target":39,"name":"eEnum"},{"source":200,"target":39,"name":"eEnum"},{"source":201,"target":39,"name":"eEnum"},{"source":202,"target":39,"name":"eEnum"},{"source":203,"target":39,"name":"eEnum"},{"source":204,"target":39,"name":"eEnum"},{"source":205,"target":39,"name":"eEnum"},{"source":206,"target":39,"name":"eEnum"},{"source":207,"target":39,"name":"eEnum"},{"source":208,"target":39,"name":"eEnum"},{"source":209,"target":39,"name":"eEnum"},{"source":210,"target":39,"name":"eEnum"},{"source":211,"target":39,"name":"eEnum"},{"source":212,"target":43,"name":"eEnum"},{"source":213,"target":43,"name":"eEnum"},{"source":214,"target":43,"name":"eEnum"},{"source":215,"target":43,"name":"eEnum"},{"source":216,"target":43,"name":"eEnum"},{"source":217,"target":43,"name":"eEnum"},{"source":218,"target":43,"name":"eEnum"},{"source":219,"target":46,"name":"eEnum"},{"source":220,"target":46,"name":"eEnum"},{"source":221,"target":51,"name":"eEnum"},{"source":222,"target":51,"name":"eEnum"},{"source":223,"target":51,"name":"eEnum"},{"source":224,"target":54,"name":"eEnum"},{"source":225,"target":54,"name":"eEnum"},{"source":226,"target":54,"name":"eEnum"},{"source":227,"target":54,"name":"eEnum"},{"source":228,"target":54,"name":"eEnum"},{"source":229,"target":54,"name":"eEnum"},{"source":230,"target":54,"name":"eEnum"},{"source":231,"target":54,"name":"eEnum"},{"source":232,"target":54,"name":"eEnum"},{"source":233,"target":54,"name":"eEnum"},{"source":234,"target":54,"name":"eEnum"},{"source":235,"target":54,"name":"eEnum"},{"source":236,"target":54,"name":"eEnum"},{"source":237,"target":57,"name":"eEnum"},{"source":238,"target":57,"name":"eEnum"},{"source":239,"target":57,"name":"eEnum"},{"source":240,"target":57,"name":"eEnum"},{"source":241,"target":57,"name":"eEnum"},{"source":242,"target":60,"name":"eEnum"},{"source":243,"target":60,"name":"eEnum"},{"source":244,"target":60,"name":"eEnum"},{"source":245,"target":60,"name":"eEnum"},{"source":246,"target":60,"name":"eEnum"},{"source":247,"target":60,"name":"eEnum"},{"source":248,"target":60,"name":"eEnum"},{"source":249,"target":60,"name":"eEnum"},{"source":250,"target":60,"name":"eEnum"},{"source":251,"target":60,"name":"eEnum"},{"source":252,"target":60,"name":"eEnum"},{"source":253,"target":60,"name":"eEnum"},{"source":254,"target":60,"name":"eEnum"},{"source":255,"target":60,"name":"eEnum"},{"source":256,"target":60,"name":"eEnum"},{"source":257,"target":60,"name":"eEnum"},{"source":258,"target":63,"name":"eEnum"},{"source":259,"target":63,"name":"eEnum"},{"source":260,"target":66,"name":"eEnum"},{"source":261,"target":66,"name":"eEnum"},{"source":262,"target":66,"name":"eEnum"},{"source":263,"target":66,"name":"eEnum"},{"source":264,"target":71,"name":"eEnum"},{"source":265,"target":71,"name":"eEnum"},{"source":266,"target":71,"name":"eEnum"},{"source":267,"target":77,"name":"eEnum"},{"source":268,"target":77,"name":"eEnum"},{"source":269,"target":80,"name":"eEnum"},{"source":270,"target":80,"name":"eEnum"},{"source":271,"target":80,"name":"eEnum"},{"source":272,"target":80,"name":"eEnum"},{"source":273,"target":80,"name":"eEnum"},{"source":274,"target":80,"name":"eEnum"},{"source":275,"target":80,"name":"eEnum"},{"source":276,"target":83,"name":"eEnum"},{"source":277,"target":83,"name":"eEnum"},{"source":278,"target":83,"name":"eEnum"},{"source":279,"target":86,"name":"eEnum"},{"source":280,"target":86,"name":"eEnum"},{"source":281,"target":86,"name":"eEnum"},{"source":282,"target":86,"name":"eEnum"},{"source":283,"target":90,"name":"eEnum"},{"source":284,"target":90,"name":"eEnum"},{"source":285,"target":95,"name":"eEnum"},{"source":286,"target":95,"name":"eEnum"},{"source":287,"target":95,"name":"eEnum"},{"source":288,"target":95,"name":"eEnum"},{"source":289,"target":95,"name":"eEnum"},{"source":290,"target":95,"name":"eEnum"},{"source":291,"target":95,"name":"eEnum"},{"source":292,"target":98,"name":"eEnum"},{"source":293,"target":98,"name":"eEnum"},{"source":294,"target":98,"name":"eEnum"},{"source":295,"target":98,"name":"eEnum"},{"source":296,"target":98,"name":"eEnum"},{"source":297,"target":98,"name":"eEnum"},{"source":298,"target":98,"name":"eEnum"},{"source":299,"target":98,"name":"eEnum"},{"source":300,"target":98,"name":"eEnum"},{"source":301,"target":101,"name":"eEnum"},{"source":302,"target":101,"name":"eEnum"},{"source":303,"target":101,"name":"eEnum"},{"source":304,"target":101,"name":"eEnum"},{"source":305,"target":101,"name":"eEnum"},{"source":306,"target":101,"name":"eEnum"},{"source":307,"target":101,"name":"eEnum"},{"source":308,"target":101,"name":"eEnum"},{"source":309,"target":101,"name":"eEnum"},{"source":310,"target":101,"name":"eEnum"},{"source":311,"target":101,"name":"eEnum"},{"source":312,"target":101,"name":"eEnum"},{"source":313,"target":101,"name":"eEnum"},{"source":314,"target":101,"name":"eEnum"},{"source":315,"target":101,"name":"eEnum"},{"source":316,"target":101,"name":"eEnum"},{"source":317,"target":101,"name":"eEnum"},{"source":318,"target":101,"name":"eEnum"},{"source":319,"target":101,"name":"eEnum"},{"source":320,"target":101,"name":"eEnum"},{"source":321,"target":101,"name":"eEnum"},{"source":322,"target":101,"name":"eEnum"},{"source":323,"target":101,"name":"eEnum"},{"source":324,"target":101,"name":"eEnum"},{"source":325,"target":101,"name":"eEnum"},{"source":326,"target":101,"name":"eEnum"},{"source":327,"target":101,"name":"eEnum"},{"source":328,"target":101,"name":"eEnum"},{"source":329,"target":101,"name":"eEnum"},{"source":330,"target":101,"name":"eEnum"},{"source":331,"target":101,"name":"eEnum"},{"source":332,"target":101,"name":"eEnum"},{"source":333,"target":101,"name":"eEnum"},{"source":334,"target":101,"name":"eEnum"},{"source":335,"target":101,"name":"eEnum"},{"source":336,"target":101,"name":"eEnum"},{"source":337,"target":101,"name":"eEnum"},{"source":338,"target":101,"name":"eEnum"},{"source":339,"target":101,"name":"eEnum"},{"source":340,"target":101,"name":"eEnum"},{"source":341,"target":101,"name":"eEnum"},{"source":342,"target":101,"name":"eEnum"},{"source":343,"target":101,"name":"eEnum"},{"source":344,"target":101,"name":"eEnum"},{"source":345,"target":104,"name":"eEnum"},{"source":346,"target":104,"name":"eEnum"},{"source":347,"target":104,"name":"eEnum"},{"source":348,"target":104,"name":"eEnum"},{"source":349,"target":107,"name":"eEnum"},{"source":350,"target":107,"name":"eEnum"},{"source":351,"target":107,"name":"eEnum"},{"source":352,"target":107,"name":"eEnum"},{"source":353,"target":107,"name":"eEnum"},{"source":354,"target":110,"name":"eEnum"},{"source":355,"target":110,"name":"eEnum"},{"source":356,"target":110,"name":"eEnum"},{"source":357,"target":115,"name":"eEnum"},{"source":358,"target":115,"name":"eEnum"},{"source":359,"target":115,"name":"eEnum"},{"source":360,"target":115,"name":"eEnum"},{"source":361,"target":118,"name":"eEnum"},{"source":362,"target":118,"name":"eEnum"},{"source":363,"target":118,"name":"eEnum"},{"source":364,"target":118,"name":"eEnum"},{"source":365,"target":118,"name":"eEnum"},{"source":366,"target":123,"name":"eEnum"},{"source":367,"target":123,"name":"eEnum"},{"source":368,"target":123,"name":"eEnum"},{"source":369,"target":126,"name":"eEnum"},{"source":370,"target":126,"name":"eEnum"},{"source":371,"target":129,"name":"eEnum"},{"source":372,"target":129,"name":"eEnum"},{"source":373,"target":129,"name":"eEnum"},{"source":374,"target":132,"name":"eEnum"},{"source":375,"target":132,"name":"eEnum"},{"source":376,"target":132,"name":"eEnum"},{"source":377,"target":132,"name":"eEnum"},{"source":378,"target":132,"name":"eEnum"},{"source":379,"target":132,"name":"eEnum"},{"source":380,"target":132,"name":"eEnum"},{"source":381,"target":132,"name":"eEnum"},{"source":382,"target":135,"name":"eEnum"},{"source":383,"target":135,"name":"eEnum"},{"source":384,"target":135,"name":"eEnum"},{"source":385,"target":135,"name":"eEnum"},{"source":386,"target":140,"name":"eEnum"},{"source":387,"target":140,"name":"eEnum"},{"source":388,"target":145,"name":"eEnum"},{"source":389,"target":145,"name":"eEnum"}],"nodeTypes":{"0":"EPackage","1":"EDataType","2":"EEnum","3":"EDataType","4":"EEnum","5":"EDataType","6":"EDataType","7":"EDataType","8":"EDataType","9":"EDataType","10":"EEnum","11":"EDataType","12":"EDataType","13":"EDataType","14":"EDataType","15":"EEnum","16":"EDataType","17":"EDataType","18":"EEnum","19":"EDataType","20":"EDataType","21":"EDataType","22":"EDataType","23":"EEnum","24":"EDataType","25":"EDataType","26":"EEnum","27":"EDataType","28":"EDataType","29":"EEnum","30":"EDataType","31":"EDataType","32":"EEnum","33":"EDataType","34":"EDataType","35":"EDataType","36":"EDataType","37":"EDataType","38":"EDataType","39":"EEnum","40":"EDataType","41":"EDataType","42":"EDataType","43":"EEnum","44":"EDataType","45":"EDataType","46":"EEnum","47":"EDataType","48":"EDataType","49":"EDataType","50":"EDataType","51":"EEnum","52":"EDataType","53":"EDataType","54":"EEnum","55":"EDataType","56":"EDataType","57":"EEnum","58":"EDataType","59":"EDataType","60":"EEnum","61":"EDataType","62":"EDataType","63":"EEnum","64":"EDataType","65":"EDataType","66":"EEnum","67":"EDataType","68":"EDataType","69":"EDataType","70":"EDataType","71":"EEnum","72":"EDataType","73":"EDataType","74":"EDataType","75":"EDataType","76":"EDataType","77":"EEnum","78":"EDataType","79":"EDataType","80":"EEnum","81":"EDataType","82":"EDataType","83":"EEnum","84":"EDataType","85":"EDataType","86":"EEnum","87":"EDataType","88":"EDataType","89":"EDataType","90":"EEnum","91":"EDataType","92":"EDataType","93":"EDataType","94":"EDataType","95":"EEnum","96":"EDataType","97":"EDataType","98":"EEnum","99":"EDataType","100":"EDataType","101":"EEnum","102":"EDataType","103":"EDataType","104":"EEnum","105":"EDataType","106":"EDataType","107":"EEnum","108":"EDataType","109":"EDataType","110":"EEnum","111":"EDataType","112":"EDataType","113":"EDataType","114":"EDataType","115":"EEnum","116":"EDataType","117":"EDataType","118":"EEnum","119":"EDataType","120":"EDataType","121":"EDataType","122":"EDataType","123":"EEnum","124":"EDataType","125":"EDataType","126":"EEnum","127":"EDataType","128":"EDataType","129":"EEnum","130":"EDataType","131":"EDataType","132":"EEnum","133":"EDataType","134":"EDataType","135":"EEnum","136":"EDataType","137":"EDataType","138":"EDataType","139":"EDataType","140":"EEnum","141":"EDataType","142":"EDataType","143":"EDataType","144":"EDataType","145":"EEnum","146":"EDataType","147":"EDataType","148":"EEnumLiteral","149":"EEnumLiteral","150":"EEnumLiteral","151":"EEnumLiteral","152":"EEnumLiteral","153":"EEnumLiteral","154":"EEnumLiteral","155":"EEnumLiteral","156":"EEnumLiteral","157":"EEnumLiteral","158":"EEnumLiteral","159":"EEnumLiteral","160":"EEnumLiteral","161":"EEnumLiteral","162":"EEnumLiteral","163":"EEnumLiteral","164":"EEnumLiteral","165":"EEnumLiteral","166":"EEnumLiteral","167":"EEnumLiteral","168":"EEnumLiteral","169":"EEnumLiteral","170":"EEnumLiteral","171":"EEnumLiteral","172":"EEnumLiteral","173":"EEnumLiteral","174":"EEnumLiteral","175":"EEnumLiteral","176":"EEnumLiteral","177":"EEnumLiteral","178":"EEnumLiteral","179":"EEnumLiteral","180":"EEnumLiteral","181":"EEnumLiteral","182":"EEnumLiteral","183":"EEnumLiteral","184":"EEnumLiteral","185":"EEnumLiteral","186":"EEnumLiteral","187":"EEnumLiteral","188":"EEnumLiteral","189":"EEnumLiteral","190":"EEnumLiteral","191":"EEnumLiteral","192":"EEnumLiteral","193":"EEnumLiteral","194":"EEnumLiteral","195":"EEnumLiteral","196":"EEnumLiteral","197":"EEnumLiteral","198":"EEnumLiteral","199":"EEnumLiteral","200":"EEnumLiteral","201":"EEnumLiteral","202":"EEnumLiteral","203":"EEnumLiteral","204":"EEnumLiteral","205":"EEnumLiteral","206":"EEnumLiteral","207":"EEnumLiteral","208":"EEnumLiteral","209":"EEnumLiteral","210":"EEnumLiteral","211":"EEnumLiteral","212":"EEnumLiteral","213":"EEnumLiteral","214":"EEnumLiteral","215":"EEnumLiteral","216":"EEnumLiteral","217":"EEnumLiteral","218":"EEnumLiteral","219":"EEnumLiteral","220":"EEnumLiteral","221":"EEnumLiteral","222":"EEnumLiteral","223":"EEnumLiteral","224":"EEnumLiteral","225":"EEnumLiteral","226":"EEnumLiteral","227":"EEnumLiteral","228":"EEnumLiteral","229":"EEnumLiteral","230":"EEnumLiteral","231":"EEnumLiteral","232":"EEnumLiteral","233":"EEnumLiteral","234":"EEnumLiteral","235":"EEnumLiteral","236":"EEnumLiteral","237":"EEnumLiteral","238":"EEnumLiteral","239":"EEnumLiteral","240":"EEnumLiteral","241":"EEnumLiteral","242":"EEnumLiteral","243":"EEnumLiteral","244":"EEnumLiteral","245":"EEnumLiteral","246":"EEnumLiteral","247":"EEnumLiteral","248":"EEnumLiteral","249":"EEnumLiteral","250":"EEnumLiteral","251":"EEnumLiteral","252":"EEnumLiteral","253":"EEnumLiteral","254":"EEnumLiteral","255":"EEnumLiteral","256":"EEnumLiteral","257":"EEnumLiteral","258":"EEnumLiteral","259":"EEnumLiteral","260":"EEnumLiteral","261":"EEnumLiteral","262":"EEnumLiteral","263":"EEnumLiteral","264":"EEnumLiteral","265":"EEnumLiteral","266":"EEnumLiteral","267":"EEnumLiteral","268":"EEnumLiteral","269":"EEnumLiteral","270":"EEnumLiteral","271":"EEnumLiteral","272":"EEnumLiteral","273":"EEnumLiteral","274":"EEnumLiteral","275":"EEnumLiteral","276":"EEnumLiteral","277":"EEnumLiteral","278":"EEnumLiteral","279":"EEnumLiteral","280":"EEnumLiteral","281":"EEnumLiteral","282":"EEnumLiteral","283":"EEnumLiteral","284":"EEnumLiteral","285":"EEnumLiteral","286":"EEnumLiteral","287":"EEnumLiteral","288":"EEnumLiteral","289":"EEnumLiteral","290":"EEnumLiteral","291":"EEnumLiteral","292":"EEnumLiteral","293":"EEnumLiteral","294":"EEnumLiteral","295":"EEnumLiteral","296":"EEnumLiteral","297":"EEnumLiteral","298":"EEnumLiteral","299":"EEnumLiteral","300":"EEnumLiteral","301":"EEnumLiteral","302":"EEnumLiteral","303":"EEnumLiteral","304":"EEnumLiteral","305":"EEnumLiteral","306":"EEnumLiteral","307":"EEnumLiteral","308":"EEnumLiteral","309":"EEnumLiteral","310":"EEnumLiteral","311":"EEnumLiteral","312":"EEnumLiteral","313":"EEnumLiteral","314":"EEnumLiteral","315":"EEnumLiteral","316":"EEnumLiteral","317":"EEnumLiteral","318":"EEnumLiteral","319":"EEnumLiteral","320":"EEnumLiteral","321":"EEnumLiteral","322":"EEnumLiteral","323":"EEnumLiteral","324":"EEnumLiteral","325":"EEnumLiteral","326":"EEnumLiteral","327":"EEnumLiteral","328":"EEnumLiteral","329":"EEnumLiteral","330":"EEnumLiteral","331":"EEnumLiteral","332":"EEnumLiteral","333":"EEnumLiteral","334":"EEnumLiteral","335":"EEnumLiteral","336":"EEnumLiteral","337":"EEnumLiteral","338":"EEnumLiteral","339":"EEnumLiteral","340":"EEnumLiteral","341":"EEnumLiteral","342":"EEnumLiteral","343":"EEnumLiteral","344":"EEnumLiteral","345":"EEnumLiteral","346":"EEnumLiteral","347":"EEnumLiteral","348":"EEnumLiteral","349":"EEnumLiteral","350":"EEnumLiteral","351":"EEnumLiteral","352":"EEnumLiteral","353":"EEnumLiteral","354":"EEnumLiteral","355":"EEnumLiteral","356":"EEnumLiteral","357":"EEnumLiteral","358":"EEnumLiteral","359":"EEnumLiteral","360":"EEnumLiteral","361":"EEnumLiteral","362":"EEnumLiteral","363":"EEnumLiteral","364":"EEnumLiteral","365":"EEnumLiteral","366":"EEnumLiteral","367":"EEnumLiteral","368":"EEnumLiteral","369":"EEnumLiteral","370":"EEnumLiteral","371":"EEnumLiteral","372":"EEnumLiteral","373":"EEnumLiteral","374":"EEnumLiteral","375":"EEnumLiteral","376":"EEnumLiteral","377":"EEnumLiteral","378":"EEnumLiteral","379":"EEnumLiteral","380":"EEnumLiteral","381":"EEnumLiteral","382":"EEnumLiteral","383":"EEnumLiteral","384":"EEnumLiteral","385":"EEnumLiteral","386":"EEnumLiteral","387":"EEnumLiteral","388":"EEnumLiteral","389":"EEnumLiteral"},"name":"/home/antolin/wakame/mde-datasets/repo-ecore-all/data/IBMAccount/StellaCommerce/WebServicesRouter/WebContent/component-services/ecore/com.ibm.commerce.oagis9.datatypes.codelists.ecore"}
